ndx_grayscalevolume/__init__.py
ndx_grayscalevolume/test.py
ndx_grayscalevolume/spec/ndx-grayscalevolume.extensions.yaml
ndx_grayscalevolume/spec/ndx-grayscalevolume.namespace.yaml
ndx_grayscalevolume-0.0.2.dist-info/LICENSE.txt
ndx_grayscalevolume-0.0.2.dist-info/METADATA
ndx_grayscalevolume-0.0.2.dist-info/WHEEL
ndx_grayscalevolume-0.0.2.dist-info/top_level.txt
ndx_grayscalevolume-0.0.2.dist-info/RECORD
