Metadata-Version: 2.1
Name: ndx-grayscalevolume
Version: 0.0.2
Summary: 3D grayscale image.
Home-page: UNKNOWN
Author: Luiz Tauffer and Ben Dichter
Author-email: ben.dichter@gmail.com
License: UNKNOWN
Platform: UNKNOWN
Classifier: Intended Audience :: Developers
Classifier: Intended Audience :: Science/Research
Requires-Dist: pynwb
